kaybee/__init__.py
kaybee/app.py
kaybee/plugins/__init__.py
kaybee/plugins/events.py
kaybee/plugins/articles/__init__.py
kaybee/plugins/articles/actions.py
kaybee/plugins/articles/article.py
kaybee/plugins/articles/author.py
kaybee/plugins/articles/base_article.py
kaybee/plugins/articles/base_article_reference.py
kaybee/plugins/articles/base_homepage.py
kaybee/plugins/articles/base_section.py
kaybee/plugins/articles/base_toctree.py
kaybee/plugins/articles/category.py
kaybee/plugins/articles/featuretiles.py
kaybee/plugins/articles/filters.py
kaybee/plugins/articles/handlers.py
kaybee/plugins/articles/homepage.py
kaybee/plugins/articles/image_type.py
kaybee/plugins/articles/jsoncatalog.py
kaybee/plugins/articles/querylist.py
kaybee/plugins/articles/section.py
kaybee/plugins/articles/sectionbox.py
kaybee/plugins/articles/sectionquery.py
kaybee/plugins/articles/settings.py
kaybee/plugins/articles/toctree.py
kaybee/plugins/articles/video_type.py
kaybee/plugins/articles/videoplayer.py
kaybee/plugins/debugdumper/__init__.py
kaybee/plugins/debugdumper/action.py
kaybee/plugins/debugdumper/handlers.py
kaybee/plugins/debugdumper/settings.py
kaybee/plugins/genericpage/__init__.py
kaybee/plugins/genericpage/action.py
kaybee/plugins/genericpage/genericpage.py
kaybee/plugins/genericpage/handlers.py
kaybee/plugins/localtemplates/__init__.py
kaybee/plugins/localtemplates/handlers.py
kaybee/plugins/postrenderer/__init__.py
kaybee/plugins/postrenderer/action.py
kaybee/plugins/postrenderer/config.py
kaybee/plugins/queries/__init__.py
kaybee/plugins/queries/handlers.py
kaybee/plugins/queries/props_model.py
kaybee/plugins/queries/service.py
kaybee/plugins/references/__init__.py
kaybee/plugins/references/base_reference.py
kaybee/plugins/references/container.py
kaybee/plugins/references/handlers.py
kaybee/plugins/references/reference.py
kaybee/plugins/resources/__init__.py
kaybee/plugins/resources/action.py
kaybee-0.1.19.dist-info/METADATA
kaybee-0.1.19.dist-info/RECORD
kaybee-0.1.19.dist-info/WHEEL
kaybee-0.1.19.dist-info/top_level.txt
