Metadata-Version: 2.1
Name: kaybee
Version: 0.1.19
Summary: Knowledgebase system for Sphinx
Home-page: https://github.com/pauleveritt/kaybee
Author: Paul Everitt
Author-email: pauleveritt@me.com
License: UNKNOWN
Keywords: sphinx blog website
Platform: UNKNOWN
Classifier: Development Status :: 3 - Alpha
Classifier: Intended Audience :: Developers
Classifier: Topic :: Software Development :: Documentation
Classifier: License :: OSI Approved :: Apache Software License
Classifier: Programming Language :: Python :: 3.6
Requires-Dist: sphinx
Requires-Dist: dectate
Requires-Dist: ruamel.yaml
Requires-Dist: pydantic
Requires-Dist: importscan
Requires-Dist: pydash
